netqasm/__init__.py
netqasm/qlink_compat.py
netqasm/typedefs.py
netqasm/typing.py
netqasm/backend/__init__.py
netqasm/backend/executor.py
netqasm/backend/messages.py
netqasm/backend/network_stack.py
netqasm/backend/qnodeos.py
netqasm/examples/__init__.py
netqasm/examples/run_examples.py
netqasm/examples/apps/__init__.py
netqasm/examples/apps/anonymous_transmission/__init__.py
netqasm/examples/apps/anonymous_transmission/app_alice.py
netqasm/examples/apps/anonymous_transmission/app_bob.py
netqasm/examples/apps/anonymous_transmission/app_charlie.py
netqasm/examples/apps/anonymous_transmission/app_david.py
netqasm/examples/apps/anonymous_transmission/src/__init__.py
netqasm/examples/apps/anonymous_transmission/src/conf.py
netqasm/examples/apps/anonymous_transmission/src/protocol.py
netqasm/examples/apps/anonymous_transmission/src/sub_protocols.py
netqasm/examples/apps/bb84/__init__.py
netqasm/examples/apps/bb84/app_alice.py
netqasm/examples/apps/bb84/app_bob.py
netqasm/examples/apps/blind_grover/__init__.py
netqasm/examples/apps/blind_grover/app_client.py
netqasm/examples/apps/blind_grover/app_server.py
netqasm/examples/apps/blind_rotation/__init__.py
netqasm/examples/apps/blind_rotation/app_client.py
netqasm/examples/apps/blind_rotation/app_server.py
netqasm/examples/apps/chsh/__init__.py
netqasm/examples/apps/chsh/app_alice.py
netqasm/examples/apps/chsh/app_bob.py
netqasm/examples/apps/chsh/app_repeater.py
netqasm/examples/apps/dist_cnot/__init__.py
netqasm/examples/apps/dist_cnot/app_controller.py
netqasm/examples/apps/dist_cnot/app_target.py
netqasm/examples/apps/link_layer_ck/__init__.py
netqasm/examples/apps/link_layer_ck/app_client.py
netqasm/examples/apps/link_layer_ck/app_server.py
netqasm/examples/apps/link_layer_md/__init__.py
netqasm/examples/apps/link_layer_md/app_client.py
netqasm/examples/apps/link_layer_md/app_server.py
netqasm/examples/apps/magic_square/__init__.py
netqasm/examples/apps/magic_square/app_player1.py
netqasm-2.1.1.dist-info/licenses/LICENSE
netqasm-2.1.1.dist-info/METADATA
netqasm-2.1.1.dist-info/WHEEL
netqasm-2.1.1.dist-info/entry_points.txt
netqasm-2.1.1.dist-info/top_level.txt
netqasm-2.1.1.dist-info/RECORD
