Metadata-Version: 2.4
Name: netqasm
Version: 2.1.1
Summary: Tool for parsing, encoding, decoding and executing NetQASM applications
Home-page: https://github.com/QuTech-Delft/netqasm
Author: QuTech
Author-email: b.vandervecht@tudelft.nl
License: MIT
License-File: LICENSE
Requires-Dist: click<9.0,>=8.0
Requires-Dist: qlink-interface<2.0,>=1.0
Requires-Dist: numpy>=1.22
Requires-Dist: scipy>=1.8
Requires-Dist: pyyaml<7.0,>=6.0
Provides-Extra: dev
Requires-Dist: pytest<8.0,>=7.1; extra == "dev"
Requires-Dist: types-PyYAML<7.0,>=6.0; extra == "dev"
Requires-Dist: flake8>=4.0; extra == "dev"
Requires-Dist: isort<5.11,>=5.10; extra == "dev"
Requires-Dist: black<22.4,>=22.3; extra == "dev"
Requires-Dist: mypy>=0.950; extra == "dev"
Provides-Extra: squidasm
Requires-Dist: squidasm>=0.10; extra == "squidasm"
Dynamic: license-file
